femtoflow/ENV_REQUIREMENTS.sh
femtoflow/PY_REQUIREMENTS
femtoflow/VERSION
femtoflow/__init__.py
femtoflow/_open_docs.py
femtoflow/layers/__init__.py
femtoflow/layers/signal_processing.py
femtoflow/notebooks/__init__.py
femtoflow/notebooks/imdb_stream.ipynb
femtoflow/notebooks/imdb_stream_custom_trainloop.ipynb
femtoflow/notebooks/mnist_dense.ipynb
femtoflow/notebooks/prune_example.ipynb
femtoflow/notebooks/prune_example_custom_trainloop.ipynb
femtoflow/notebooks/quantization_example.ipynb
femtoflow/quantization/__init__.py
femtoflow/quantization/quantize_tflite.py
femtoflow/sparsity/__init__.py
femtoflow/sparsity/prune.py
femtoflow/sparsity/pruning_schedulers/__init__.py
femtoflow/sparsity/pruning_schedulers/linear_scheduler.py
femtoflow/sparsity/pruning_schedulers/sine_scheduler.py
femtoflow/utils/__init__.py
femtoflow/utils/metrics.py
femtoflow/utils/plot.py
test/__init__.py
test/test_notebooks.py
test/test_package.py
test/test_prune.py
test/test_quantize.py
test/test_signal_processing.py
femtoflow-0.1.8.dist-info/LICENSE
femtoflow-0.1.8.dist-info/METADATA
femtoflow-0.1.8.dist-info/WHEEL
femtoflow-0.1.8.dist-info/top_level.txt
femtoflow-0.1.8.dist-info/RECORD
