Metadata-Version: 2.1
Name: femtoflow
Version: 0.1.8
Summary: Femtosense Model Optimization Toolkit
Home-page: https://github.com/femtosense/femtoflow
Author: Femtosense
Author-email: info@femtosense.ai
Project-URL: Source, https://github.com/femtosense/femtoflow
Classifier: Development Status :: 3 - Alpha
Classifier: Intended Audience :: Developers
Classifier: Programming Language :: Python :: 3.6
Classifier: Programming Language :: Python :: 3.7
Classifier: Programming Language :: Python :: 3.8
Classifier: Programming Language :: Python :: 3 :: Only
Classifier: Operating System :: OS Independent
Requires-Python: >=3.6
License-File: LICENSE
Requires-Dist: Cython
Requires-Dist: numpy
Requires-Dist: tensorflow
Requires-Dist: tensorflow-model-optimization
Requires-Dist: matplotlib
Requires-Dist: python-speech-features
Requires-Dist: parameterized
Requires-Dist: pytest
Requires-Dist: testbook
Requires-Dist: notebook
Requires-Dist: scipy
Requires-Dist: femtocrux
